any_agent/__init__.py
any_agent/__main__.py
any_agent/cli.py
any_agent/adapters/__init__.py
any_agent/adapters/aws_strands_adapter.py
any_agent/adapters/aws_strands_adapter_backup.py
any_agent/adapters/base.py
any_agent/adapters/crewai_adapter.py
any_agent/adapters/google_adk_adapter.py
any_agent/adapters/google_adk_adapter_backup.py
any_agent/adapters/langchain_adapter.py
any_agent/adapters/langgraph_adapter.py
any_agent/api/__init__.py
any_agent/api/chat_handler.py
any_agent/api/unified_a2a_client_helper.py
any_agent/core/__init__.py
any_agent/core/agent_context.py
any_agent/core/agent_remover.py
any_agent/core/context_aware_wrapper.py
any_agent/core/context_manager.py
any_agent/core/dependency_installer.py
any_agent/core/docker_orchestrator.py
any_agent/core/env_loader.py
any_agent/core/framework_detector.py
any_agent/core/localhost_orchestrator.py
any_agent/core/port_checker.py
any_agent/core/url_translator.py
any_agent/docker/__init__.py
any_agent/docker/docker_generator.py
any_agent/localhost/__init__.py
any_agent/localhost/fastapi_generator.py
any_agent/localhost/file_watcher.py
any_agent/localhost/server.py
any_agent/localhost/ui_dev_server.py
any_agent/shared/__init__.py
any_agent/shared/chat_endpoints_generator.py
any_agent/shared/entrypoint_templates.py
any_agent/shared/module_boundaries.py
any_agent/shared/strands_context_executor.py
any_agent/shared/ui_routes_generator.py
any_agent/shared/unified_ui_routes.py
any_agent/shared/url_builder.py
any_agent/shared/url_utils.py
any_agent/ui/__init__.py
any_agent/ui/__main__.py
any_agent/ui/cli.py
any_agent/ui/index.html
any_agent/ui/manager.py
any_agent/validation/README.md
any_agent/validation/__init__.py
any_agent/validation/a2a_message_validator.py
any_agent/validation/adk_client.py
any_agent/validation/cli.py
any_agent/validation/client.py
any_agent/validation/engine.py
any_agent/validation/enhanced_client.py
any_agent/validation/pytest_plugin.py
any_agent/validation/validator.py
any_agent_wrapper-0.2.10.dist-info/METADATA
any_agent_wrapper-0.2.10.dist-info/WHEEL
any_agent_wrapper-0.2.10.dist-info/entry_points.txt
any_agent_wrapper-0.2.10.dist-info/licenses/LICENSE
any_agent_wrapper-0.2.10.dist-info/RECORD
